MANIFEST.in
README.rst
setup.py
aliyun_python_sdk_aliyuncvc.egg-info/PKG-INFO
aliyun_python_sdk_aliyuncvc.egg-info/SOURCES.txt
aliyun_python_sdk_aliyuncvc.egg-info/dependency_links.txt
aliyun_python_sdk_aliyuncvc.egg-info/requires.txt
aliyun_python_sdk_aliyuncvc.egg-info/top_level.txt
aliyunsdkaliyuncvc/__init__.py
aliyunsdkaliyuncvc/endpoint.py
aliyunsdkaliyuncvc/request/__init__.py
aliyunsdkaliyuncvc/request/v20191030/ActiveDeviceRequest.py
aliyunsdkaliyuncvc/request/v20191030/ActiveMeetingRequest.py
aliyunsdkaliyuncvc/request/v20191030/BatchCreateDeviceRequest.py
aliyunsdkaliyuncvc/request/v20191030/CallDeviceRequest.py
aliyunsdkaliyuncvc/request/v20191030/ConferenceToLiveRequest.py
aliyunsdkaliyuncvc/request/v20191030/CreateDeviceMeetingRequest.py
aliyunsdkaliyuncvc/request/v20191030/CreateEvaluationRequest.py
aliyunsdkaliyuncvc/request/v20191030/CreateLiveRequest.py
aliyunsdkaliyuncvc/request/v20191030/CreateMeetingInternationalRequest.py
aliyunsdkaliyuncvc/request/v20191030/CreateMeetingRequest.py
aliyunsdkaliyuncvc/request/v20191030/CreateUserInternationalRequest.py
aliyunsdkaliyuncvc/request/v20191030/CreateUserRequest.py
aliyunsdkaliyuncvc/request/v20191030/CustomGonggeLayoutRequest.py
aliyunsdkaliyuncvc/request/v20191030/CustomLayoutRequest.py
aliyunsdkaliyuncvc/request/v20191030/DeleteDeviceRequest.py
aliyunsdkaliyuncvc/request/v20191030/DeleteLiveRequest.py
aliyunsdkaliyuncvc/request/v20191030/DeleteMeetingRequest.py
aliyunsdkaliyuncvc/request/v20191030/DeleteUserRequest.py
aliyunsdkaliyuncvc/request/v20191030/EnableLiveSpeakerRequest.py
aliyunsdkaliyuncvc/request/v20191030/EndDeviceMeetingRequest.py
aliyunsdkaliyuncvc/request/v20191030/EndLiveRequest.py
aliyunsdkaliyuncvc/request/v20191030/GetAccountInfoRequest.py
aliyunsdkaliyuncvc/request/v20191030/GetDeviceActiveCodeRequest.py
aliyunsdkaliyuncvc/request/v20191030/GetDeviceInfoRequest.py
aliyunsdkaliyuncvc/request/v20191030/GetDeviceTokenRequest.py
aliyunsdkaliyuncvc/request/v20191030/GetMeetingInternationalRequest.py
aliyunsdkaliyuncvc/request/v20191030/GetMeetingMemberRequest.py
aliyunsdkaliyuncvc/request/v20191030/GetMeetingRequest.py
aliyunsdkaliyuncvc/request/v20191030/GetStatisticRequest.py
